cuke4behave/__init__.py
cuke4behave/step_matcher.py
cuke4behave-0.1.3.dist-info/LICENSE.md
cuke4behave-0.1.3.dist-info/WHEEL
cuke4behave-0.1.3.dist-info/METADATA
cuke4behave-0.1.3.dist-info/RECORD
