Metadata-Version: 2.1
Name: cuke4behave
Version: 0.1.3
Summary: Give Behave the power of Cucumber Expressions
License: MIT
Keywords: License :: OSI Approved :: MIT License,Development Status :: 4 - Beta,Intended Audience :: Developers
Author: Dev Kumar Gupta
Requires-Python: >=3.7,<4.0
Classifier: License :: OSI Approved :: MIT License
Classifier: Programming Language :: Python :: 3
Classifier: Programming Language :: Python :: 3.10
Classifier: Programming Language :: Python :: 3.7
Classifier: Programming Language :: Python :: 3.8
Classifier: Programming Language :: Python :: 3.9
Requires-Dist: behave (==1.2.6)
Requires-Dist: cucumber-expressions (==16.0.0)
